akinaka/__init__.py
akinaka/main.py
akinaka/cleanup/__init__.py
akinaka/cleanup/commands.py
akinaka/cleanup/ami/__init__.py
akinaka/cleanup/ami/cleanup_amis.py
akinaka/cleanup/ebs/__init__.py
akinaka/cleanup/ebs/cleanup_volumes.py
akinaka/cleanup/rds/__init__.py
akinaka/cleanup/rds/cleanup_snapshots.py
akinaka/client/__init__.py
akinaka/client/aws_client.py
akinaka/container/__init__.py
akinaka/container/commands.py
akinaka/container/ecr/__init__.py
akinaka/container/ecr/ecr_login.py
akinaka/dr/__init__.py
akinaka/dr/commands.py
akinaka/dr/rds/__init__.py
akinaka/dr/rds/transfer_snapshot.py
akinaka/dr/s3/__init__.py
akinaka/dr/s3/transfer_s3.py
akinaka/k8s/__init__.py
akinaka/k8s/commands.py
akinaka/k8s/deployment/__init__.py
akinaka/k8s/deployment/deployment.py
akinaka/k8s/manifest/__init__.py
akinaka/k8s/manifest/manifest.py
akinaka/libs/__init__.py
akinaka/libs/cloudwatch.py
akinaka/libs/costexplorer.py
akinaka/libs/exceptions.py
akinaka/libs/helpers.py
akinaka/libs/kms_share.py
akinaka/libs/scan_resources_storage.py
akinaka/rds/__init__.py
akinaka/rds/commands.py
akinaka/rds/copy/__init__.py
akinaka/rds/copy/copy_rds.py
akinaka/reporting/__init__.py
akinaka/reporting/commands.py
akinaka/reporting/billing_summary/__init__.py
akinaka/reporting/billing_summary/billing_queries.py
akinaka/update/__init__.py
akinaka/update/commands.py
akinaka/update/asg/__init__.py
akinaka/update/asg/update_asg.py
akinaka/update/targetgroup/__init__.py
akinaka/update/targetgroup/update_targetgroup.py
akinaka-1.0.1.dist-info/LICENSE
akinaka-1.0.1.dist-info/METADATA
akinaka-1.0.1.dist-info/WHEEL
akinaka-1.0.1.dist-info/entry_points.txt
akinaka-1.0.1.dist-info/top_level.txt
akinaka-1.0.1.dist-info/RECORD
