Metadata-Version: 2.1
Name: akinaka
Version: 1.0.1
Summary: Useful AWS CLI Extras
Home-page: https://github.com/afrazkhan/akinaka
Author: Afraz
Author-email: afrazkhan@gmail.com
License: UNKNOWN
Keywords: aws
Platform: UNKNOWN
Classifier: Programming Language :: Python :: 3
Classifier: License :: OSI Approved :: GNU General Public License v3 or later (GPLv3+)
Classifier: Operating System :: OS Independent
Requires-Python: >=3.3.0
License-File: LICENSE
Requires-Dist: boto3
Requires-Dist: datetime
Requires-Dist: click
Requires-Dist: pyyaml
Requires-Dist: kubernetes
Requires-Dist: slack-sdk
Requires-Dist: messagebird
